pyFMST/__init__.py
pyFMST/main.py
pyFMST/fmstUtils/__init__.py
pyFMST/fmstUtils/fmstUtils.py
pyFMST/fmstUtils/genUtils.py
pyfmst-0.1.1.dist-info/METADATA
pyfmst-0.1.1.dist-info/WHEEL
pyfmst-0.1.1.dist-info/top_level.txt
pyfmst-0.1.1.dist-info/RECORD
