Metadata-Version: 2.4
Name: pyFMST
Version: 0.1.1
Summary: Python wrapper for FMST
Author: Will Pizii
License: GPL-3.0-or-later
Requires-Dist: pygmt
Requires-Dist: matplotlib
Requires-Dist: numpy
Requires-Dist: pandas
Requires-Dist: obspy
Requires-Dist: tqdm
